topsis_rohanmalhotra_102303437/__init__.py
topsis_rohanmalhotra_102303437/cli.py
topsis_rohanmalhotra_102303437/core.py
topsis_rohanmalhotra_102303437-1.0.0.dist-info/licenses/LICENSE
topsis_rohanmalhotra_102303437-1.0.0.dist-info/METADATA
topsis_rohanmalhotra_102303437-1.0.0.dist-info/WHEEL
topsis_rohanmalhotra_102303437-1.0.0.dist-info/entry_points.txt
topsis_rohanmalhotra_102303437-1.0.0.dist-info/top_level.txt
topsis_rohanmalhotra_102303437-1.0.0.dist-info/RECORD
