Metadata-Version: 2.4
Name: Topsis-RohanMalhotra-102303437
Version: 1.0.0
Summary: TOPSIS implementation (CLI)
Author-email: Rohan Malhotra <rmalhotra1_be23@thapar.edu>
License: MIT
Project-URL: Homepage, https://pypi.org/
Requires-Python: >=3.8
License-File: LICENSE
Requires-Dist: pandas>=1.5
Dynamic: license-file
